pfsubset/__init__.py
pfsubset/subset/__init__.py
pfsubset/subset/bbox.py
pfsubset/subset/clipper.py
pfsubset/subset/domain.py
pfsubset/subset/mask.py
pfsubset/subset/rasterizer.py
pfsubset/subset/data/__init__.py
pfsubset/subset/data/conus_manifest.yaml
pfsubset/subset/data/parking_lot_template.py
pfsubset/subset/tools/__init__.py
pfsubset/subset/tools/bulk_clipper.py
pfsubset/subset/tools/rasterize_shape.py
pfsubset/subset/tools/subset_conus.py
pfsubset/subset/utils/__init__.py
pfsubset/subset/utils/arguments.py
pfsubset/subset/utils/huc2shape.py
pfsubset/subset/utils/io.py
parflow_subsetter-1.0.0.dist-info/METADATA
parflow_subsetter-1.0.0.dist-info/WHEEL
parflow_subsetter-1.0.0.dist-info/top_level.txt
parflow_subsetter-1.0.0.dist-info/RECORD
