Metadata-Version: 2.1
Name: parflow-subsetter
Version: 1.0.0
Summary: A set of tools for clipping ParFlow model inputs and outputs
Home-page: https://github.com/hydroframe/Subsetting
Author: HydroFrame Team
Author-email: parflow@parflow.org
License: UNKNOWN
Platform: UNKNOWN
Classifier: Programming Language :: Python :: 3
Classifier: License :: OSI Approved :: MIT License
Classifier: Operating System :: OS Independent
Requires-Python: >=3.6
Requires-Dist: pyyaml (>=5.3.0)
Requires-Dist: pandas (>=1.0)
Requires-Dist: parflowio (>=0.0.4)
Requires-Dist: pftools (>=1.0.0)
